{
  "week": 7,
  "generated_date": "2025-11-28",
  "candidates": [
    {
      "ticker": "AVGO",
      "name": "Broadcom Inc.",
      "sector": "Technology",
      "market_cap_billions": 785.5,
      "avg_volume_millions": 3.2,
      "momentum_4w_pct": 12.3,
      "momentum_12w_pct": 28.7,
      "qualitative_research": "AI semiconductor leader with strong data center GPU demand. Recent earnings beat expectations with 20% revenue growth.",
      "source": "websearch",
      "investors_holding": 4380,
      "holder_changes": "increasing",
      "industry": "Semiconductors",
      "description": "Broadcom Inc. designs, develops, and supplies various semiconductor devices and infrastructure software solutions worldwide. The company operates in two segments, Semiconductor Solutions and Infrastructure Software. It provides Ethernet switching and...",
      "website": "https://www.broadcom.com",
      "employees": 37000,
      "country": "United States",
      "pe_ratio_forward": 65.31,
      "pb_ratio": 6.8,
      "market_cap": 1902924136448,
      "profit_margin_pct": 31.59,
      "roe_pct": 27.08,
      "roa_pct": 8.9,
      "operating_margin_pct": 31.77,
      "revenue_growth_yoy": 16.4,
      "earnings_growth_yoy": 188.1,
      "debt_equity_ratio": 1.66,
      "current_ratio": 1.5,
      "cash_millions": 11105.0,
      "debt_millions": 40457.0,
      "beta": 1.21,
      "dividend_yield_pct": 59.0,
      "year_high": 403.0,
      "year_low": 138.1
    },
    {
      "ticker": "PLTR",
      "name": "Palantir Technologies",
      "sector": "Technology",
      "market_cap_billions": 89.4,
      "avg_volume_millions": 54.8,
      "momentum_4w_pct": 8.5,
      "momentum_12w_pct": -5.2,
      "qualitative_research": "AI platform provider with government and commercial contracts. Currently held in portfolio.",
      "source": "existing_position",
      "investors_holding": 2951,
      "holder_changes": "increasing",
      "industry": "Software - Infrastructure",
      "description": "Palantir Technologies Inc. builds and deploys software platforms for the intelligence community to assist in counterterrorism investigations and operations in the United States, the United Kingdom, and internationally. It provides Palantir Gotham, a ...",
      "website": "https://www.palantir.com",
      "employees": 4414,
      "country": "United States",
      "pe_ratio_forward": 358.4,
      "pb_ratio": 60.92,
      "market_cap": 401489821696,
      "profit_margin_pct": 28.11,
      "roe_pct": 19.5,
      "roa_pct": 7.65,
      "operating_margin_pct": 33.3,
      "revenue_growth_yoy": 62.8,
      "earnings_growth_yoy": 200.0,
      "debt_equity_ratio": 0.04,
      "current_ratio": 6.43,
      "cash_millions": 6437.8,
      "debt_millions": 235.4,
      "beta": 1.48,
      "year_high": 207.52,
      "year_low": 63.4
    },
    {
      "ticker": "MSTR",
      "name": "MicroStrategy Inc.",
      "sector": "Technology",
      "market_cap_billions": 42.1,
      "avg_volume_millions": 18.5,
      "momentum_4w_pct": 45.2,
      "momentum_12w_pct": 138.5,
      "qualitative_research": "Bitcoin treasury strategy company. Extreme volatility with Bitcoin correlation.",
      "source": "websearch",
      "investors_holding": 1233,
      "holder_changes": "decreasing",
      "industry": "Software - Application",
      "description": "Strategy Inc, together with its subsidiaries, operates as a bitcoin treasury company in the United States, Europe, the Middle East, Africa, and internationally. The company offers investors varying degrees of economic exposure to Bitcoin by offering ...",
      "website": "https://www.strategy.com",
      "employees": 1546,
      "country": "United States",
      "pe_ratio_forward": -412.05,
      "pb_ratio": 0.97,
      "market_cap": 50913333248,
      "profit_margin_pct": 1667.09,
      "roe_pct": 25.59,
      "roa_pct": 16.75,
      "operating_margin_pct": 3023.4,
      "revenue_growth_yoy": 10.9,
      "debt_equity_ratio": 0.14,
      "current_ratio": 0.66,
      "cash_millions": 54.3,
      "debt_millions": 8222.1,
      "beta": 3.37,
      "year_high": 457.22,
      "year_low": 166.01
    }
  ],
  "enrichment": {
    "octagon_ai": {
      "timestamp": "2025-11-29T15:59:09.074158",
      "week": 7,
      "total": 3,
      "enriched": 3,
      "failed": 0,
      "fields_added": 6
    },
    "fmp": {
      "timestamp": "2025-11-29T16:15:41.882462",
      "week": 7,
      "total": 3,
      "enriched": 0,
      "failed": 3,
      "fields_added": 0
    },
    "yahoo_finance": {
      "timestamp": "2025-11-29T16:20:42.105163",
      "week": 7,
      "total": 3,
      "enriched": 3,
      "failed": 0,
      "fields_added": 66
    }
  }
}
